binomialbias/__init__.py
binomialbias/app.py
binomialbias/main.py
binomialbias/version.py
binomialbias-1.3.3.dist-info/LICENSE
binomialbias-1.3.3.dist-info/METADATA
binomialbias-1.3.3.dist-info/WHEEL
binomialbias-1.3.3.dist-info/top_level.txt
binomialbias-1.3.3.dist-info/RECORD
