Metadata-Version: 2.1
Name: binomialbias
Version: 1.3.3
Summary: Quantitative assessment of discrimination based on the binomial distribution
Home-page: http://binomialbias.sciris.org
Author: P.A. Robinson, C. C. Kerr
Author-email: cliff@thekerrlab.com
Keywords: binomial distribution,discrimination,bias,sexism,racism
Platform: OS Independent
Classifier: Environment :: Console
Classifier: Intended Audience :: Science/Research
Classifier: License :: Other/Proprietary License
Classifier: Operating System :: OS Independent
Classifier: Topic :: Software Development :: Libraries :: Python Modules
Classifier: Development Status :: 5 - Production/Stable
Classifier: Programming Language :: Python
Classifier: Programming Language :: Python :: 3.11
License-File: LICENSE
Requires-Dist: numpy
Requires-Dist: scipy
Requires-Dist: matplotlib
Requires-Dist: sciris
Provides-Extra: app
Requires-Dist: shiny ; extra == 'app'
Requires-Dist: rsconnect-python ; extra == 'app'
